redis_circular_list/__init__.py
redis_circular_list-0.0.4.dist-info/METADATA
redis_circular_list-0.0.4.dist-info/WHEEL
redis_circular_list-0.0.4.dist-info/top_level.txt
redis_circular_list-0.0.4.dist-info/RECORD
