Metadata-Version: 2.1
Name: redis-circular-list
Version: 0.0.4
Summary: Redis Circular List
Home-page: https://github.com/48723247842/RedisCirclularList
Author: 7435171
Author-email: 48723247842@protonmail.com
License: UNKNOWN
Platform: UNKNOWN
Classifier: Programming Language :: Python :: 3
Classifier: License :: OSI Approved :: MIT License
Classifier: Operating System :: OS Independent
Requires-Python: >=3.8
